fontsize/__init__.py
fontsize/__main__.py
fontsize/size.py
font_size-0.1.2.dist-info/LICENSE
font_size-0.1.2.dist-info/METADATA
font_size-0.1.2.dist-info/WHEEL
font_size-0.1.2.dist-info/entry_points.txt
font_size-0.1.2.dist-info/top_level.txt
font_size-0.1.2.dist-info/RECORD
