Metadata-Version: 2.1
Name: font-size
Version: 0.1.2
Summary: Font file and OpenType table size reporting tool
Home-page: https://github.com/source-foundry/font-size
Author: Source Foundry Authors
Author-email: chris@sourcefoundry.org
License: Apache License v2.0
Platform: Any
Classifier: Development Status :: 4 - Beta
Classifier: Environment :: Console
Classifier: Intended Audience :: Developers
Classifier: Intended Audience :: End Users/Desktop
Classifier: License :: OSI Approved :: Apache Software License
Classifier: Natural Language :: English
Classifier: Operating System :: OS Independent
Classifier: Programming Language :: Python
Classifier: Programming Language :: Python :: 3
Classifier: Programming Language :: Python :: 3.6
Classifier: Programming Language :: Python :: 3.7
Classifier: Programming Language :: Python :: 3.8
Classifier: Programming Language :: Python :: 3.9
Requires-Python: >=3.6.0
Provides-Extra: dev
Provides-Extra: maintain
License-File: LICENSE
